simputils/config/__init__.py
simputils/config/base.py
simputils/config/types.py
simputils/config/components/ConfigHub.py
simputils/config/components/__init__.py
simputils/config/components/handlers/DotEnvFileHandler.py
simputils/config/components/handlers/JsonFileHandler.py
simputils/config/components/handlers/YamlFileHandler.py
simputils/config/components/handlers/__init__.py
simputils/config/components/preprocessors/SimputilsCastingPreprocessor.py
simputils/config/components/preprocessors/SimputilsStandardPreprocessor.py
simputils/config/components/preprocessors/__init__.py
simputils/config/components/prisms/ObjConfigStorePrism.py
simputils/config/components/prisms/__init__.py
simputils/config/components/simpletons/NotExisting.py
simputils/config/components/simpletons/__init__.py
simputils/config/components/strategies/MergingStrategyFlat.py
simputils/config/components/strategies/MergingStrategyRecursive.py
simputils/config/components/strategies/__init__.py
simputils/config/enums/ConfigStoreType.py
simputils/config/enums/MergingStrategiesEnum.py
simputils/config/enums/__init__.py
simputils/config/exceptions/NoAvailableHandlers.py
simputils/config/exceptions/NoHandler.py
simputils/config/exceptions/NotPermitted.py
simputils/config/exceptions/StrictKeysEnabled.py
simputils/config/exceptions/WrongFormat.py
simputils/config/exceptions/__init__.py
simputils/config/generic/BasicAppliedConf.py
simputils/config/generic/BasicConditional.py
simputils/config/generic/BasicConfigEnum.py
simputils/config/generic/BasicConfigStore.py
simputils/config/generic/BasicFileHandler.py
simputils/config/generic/BasicMergingStrategy.py
simputils/config/generic/BasicPreprocessor.py
simputils/config/generic/__init__.py
simputils/config/models/AnnotatedConfigData.py
simputils/config/models/AppliedConf.py
simputils/config/models/ConfigStore.py
simputils/config/models/__init__.py
simputils_config-1.1.1.dist-info/LICENSE
simputils_config-1.1.1.dist-info/METADATA
simputils_config-1.1.1.dist-info/WHEEL
simputils_config-1.1.1.dist-info/top_level.txt
simputils_config-1.1.1.dist-info/RECORD
