Metadata-Version: 2.1
Name: simputils-config
Version: 1.1.1
Summary: Simple Configs Manager
Author-email: Ivan Ponomarev <i.ponomarev@pandev.tech>
License: MIT License
Project-URL: Homepage, https://github.com/PandaHugMonster/py-simputils-config
Project-URL: Issues, https://github.com/PandaHugMonster/py-simputils-config/issues
Keywords: simputils,config,files,utils,framework,simple
Classifier: Programming Language :: Python :: 3
Classifier: License :: OSI Approved :: MIT License
Classifier: Operating System :: OS Independent
Requires-Python: >=3.10
License-File: LICENSE
Requires-Dist: pyyaml
Requires-Dist: python-magic
Requires-Dist: python-dotenv
Provides-Extra: dev
Requires-Dist: pytest ; extra == 'dev'
Requires-Dist: pytest-cov ; extra == 'dev'
Requires-Dist: flake8 ; extra == 'dev'
Provides-Extra: pydantic
Requires-Dist: pydantic ; extra == 'pydantic'
